LICENSE
README.md
setup.py
NlpToolkit_SpellChecker_Cy.egg-info/PKG-INFO
NlpToolkit_SpellChecker_Cy.egg-info/SOURCES.txt
NlpToolkit_SpellChecker_Cy.egg-info/dependency_links.txt
NlpToolkit_SpellChecker_Cy.egg-info/requires.txt
NlpToolkit_SpellChecker_Cy.egg-info/top_level.txt
SpellChecker/Candidate.c
SpellChecker/Candidate.pxd
SpellChecker/Candidate.pyx
SpellChecker/ContextBasedSpellChecker.c
SpellChecker/ContextBasedSpellChecker.pxd
SpellChecker/ContextBasedSpellChecker.pyx
SpellChecker/NGramSpellChecker.c
SpellChecker/NGramSpellChecker.pxd
SpellChecker/NGramSpellChecker.pyx
SpellChecker/Operator.py
SpellChecker/SimpleSpellChecker.c
SpellChecker/SimpleSpellChecker.pxd
SpellChecker/SimpleSpellChecker.pyx
SpellChecker/SpellChecker.c
SpellChecker/SpellChecker.pxd
SpellChecker/SpellChecker.pyx
SpellChecker/SpellCheckerParameter.c
SpellChecker/SpellCheckerParameter.pxd
SpellChecker/SpellCheckerParameter.pyx
SpellChecker/Trie.c
SpellChecker/Trie.pxd
SpellChecker/Trie.pyx
SpellChecker/TrieBasedSpellChecker.c
SpellChecker/TrieBasedSpellChecker.pxd
SpellChecker/TrieBasedSpellChecker.pyx
SpellChecker/TrieCandidate.c
SpellChecker/TrieCandidate.pxd
SpellChecker/TrieCandidate.pyx
SpellChecker/TrieNode.c
SpellChecker/TrieNode.pxd
SpellChecker/TrieNode.pyx
SpellChecker/__init__.py
nlptoolkit_spellchecker_cy.egg-info/PKG-INFO
nlptoolkit_spellchecker_cy.egg-info/SOURCES.txt
nlptoolkit_spellchecker_cy.egg-info/dependency_links.txt
nlptoolkit_spellchecker_cy.egg-info/requires.txt
nlptoolkit_spellchecker_cy.egg-info/top_level.txt